setup.py
tekton/__init__.py
tekton/router.py
tekton.egg-info/PKG-INFO
tekton.egg-info/SOURCES.txt
tekton.egg-info/dependency_links.txt
tekton.egg-info/not-zip-safe
tekton.egg-info/top_level.txt
tekton/gae/__init__.py
tekton/gae/middleware/__init__.py
tekton/gae/middleware/email_errors.py
tekton/gae/middleware/json_middleware.py
tekton/gae/middleware/parameter.py
tekton/gae/middleware/redirect.py
tekton/gae/middleware/response.py
tekton/gae/middleware/router_middleware.py
tekton/gae/middleware/webapp2_dependencies.py